manual_spellchecker.py
manual_spellchecker-1.2.dist-info/LICENSE
manual_spellchecker-1.2.dist-info/METADATA
manual_spellchecker-1.2.dist-info/WHEEL
manual_spellchecker-1.2.dist-info/top_level.txt
manual_spellchecker-1.2.dist-info/RECORD
