Metadata-Version: 2.1
Name: manual-spellchecker
Version: 1.2
Summary: A manual spell checker built on pyenchant that allows you to swiftly correct misspelled words.
Home-page: https://github.com/atif-hassan/manual_spellchecker
Author: Atif Hassan
Author-email: atif.hit.hassan@gmail.com
License: UNKNOWN
Platform: UNKNOWN
Classifier: Programming Language :: Python :: 3
Classifier: Programming Language :: Python :: 3.6
Classifier: Programming Language :: Python :: 3.7
Classifier: License :: OSI Approved :: GNU Lesser General Public License v2 or later (LGPLv2+)
Classifier: Operating System :: OS Independent
Requires-Dist: tqdm
Requires-Dist: pyenchant
Requires-Dist: numpy
